[
	{"formname":"leftPane", "fieldname":"mainfilter", "text":"Filter sessions-courses..."},
	{"formname":"leftPane", "fieldname":"maintitle", "text":"Sessions-Courses"},
	{"formname":"leftPane", "fieldname":"noresult", "text":"No session-course found"},

	{"formname":"main", "fieldname":"msgformdirty", "text":"Modifications have not been saved. Do you really want to leave?"},
	{"formname":"main", "fieldname":"msgdeletesession", "text":"Do you really want to delete this session-course?"},
	{"formname":"main", "fieldname":"msgnofilter", "text":"No filter defined"},
	{"formname":"main", "fieldname":"formtitledetails", "text":"Session Course Details"},

	{"formname":"sessioncourses", "fieldname":"buttontitlereports", "text":"reports"},
	{"formname":"sessioncourses", "fieldname":"reporttitlesessioncourselist", "text":"List of Skaters for the Course"},
	{"formname":"sessioncourses", "fieldname":"reporttitlesessioncourselistactive", "text":"List of Active Skaters for the Course"},
	{"formname":"sessioncourses", "fieldname":"reporttitlesessioncourseschedule", "text":"Schedule of the Course"},
	{"formname":"sessioncourses", "fieldname":"reportdividerattendance", "text":"Attendance"},
	{"formname":"sessioncourses", "fieldname":"reporttitlesessioncourseattendance", "text":"Course Attendance"},
	{"formname":"sessioncourses", "fieldname":"reporttitlesessioncourseattendancesub", "text":"Course Attendance by Sublevels"},
	{"formname":"sessioncourses", "fieldname":"reportdividercanskatecourse", "text":"CanSkate Courses"},
	{"formname":"sessioncourses", "fieldname":"reporttitlecanskateprogressreport", "text":"Course CanSkate Progress Card"},
	{"formname":"sessioncourses", "fieldname":"reporttitlecanskatereportcard", "text":"Course Canskate Progress Report"},
	{"formname":"sessioncourses", "fieldname":"reporttitleprecanskatereportcard", "text":"Course Pre-Canskate Progress Report"},
	{"formname":"sessioncourses", "fieldname":"reporttitlesessionnumberlist", "text":"List of Skaters for the Number"},
	{"formname":"sessioncourses", "fieldname":"reporttitlesessionnumberlistactive", "text":"List of Active Skaters for the Number"},
	{"formname":"sessioncourses", "fieldname":"reporttitlesessionnumberschedule", "text":"Schedule of the Number"},
	{"formname":"sessioncourses", "fieldname":"reporttitlesessionnumberattendance", "text":"Number Attendance"},
	{"formname":"sessioncourses", "fieldname":"tabtitleskaterlist", "text":"Skaters"},
	{"formname":"sessioncourses", "fieldname":"tabtitlecoachesandap", "text":"Coaches and PAs"},
	{"formname":"sessioncourses", "fieldname":"fieldeventname", "text":"Event"},

	{"formname":"details", "fieldname":"labelcourse", "text":"Course"},
	{"formname":"details", "fieldname":"labelenglishlabel", "text":"English Label"},
	{"formname":"details", "fieldname":"labelfrenchlabel", "text":"French Label"},
	{"formname":"details", "fieldname":"labelfees", "text":"Fees"},
	{"formname":"details", "fieldname":"labelnbofskaters", "text":"Nb of Skaters"},
	{"formname":"details", "fieldname":"labelskater", "text":"Skater"},
	{"formname":"details", "fieldname":"labelsublevel", "text":"Sublevel"},
	{"formname":"details", "fieldname":"coursetype", "text":"Type"},
	{"formname":"details", "fieldname":"courselevel", "text":"Level"},
	{"formname":"details", "fieldname":"shownumber", "text":"Show Number"},

	{"formname":"coachform", "fieldname":"labelcourse", "text":"Course"},
	{"formname":"coachform", "fieldname":"labelenglishlabel", "text":"English Label"},
	{"formname":"coachform", "fieldname":"labelfrenchlabel", "text":"French Label"},
	{"formname":"coachform", "fieldname":"labelfees", "text":"Fees"},
	{"formname":"coachform", "fieldname":"labelnbofskaters", "text":"Nb of Skaters"},
	{"formname":"coachform", "fieldname":"labelskater", "text":"Skater"},
	{"formname":"coachform", "fieldname":"labelsublevel", "text":"Sublevel"},
	{"formname":"coachform", "fieldname":"titlestaff", "text":"Staff (permanent)"},
	{"formname":"coachform", "fieldname":"titlestaffrepl", "text":"Staff (replacement)"}

]
